{
  "scene": "lava-temple-oracle",
  "output": "/workspace/output/examples/lava-temple-oracle.avif",
  "schema_version": 2,
  "hardware": {
    "gpu": "NVIDIA GB200",
    "compute_capability": "10.0"
  },
  "versions": {
    "driver": "595.84.01",
    "cuda_driver_api": 13020,
    "cuda_runtime": 13000,
    "optix": 90100
  },
  "render": {
    "width": 3840,
    "height": 2160,
    "spp": 2048,
    "max_depth": 12,
    "seed": 909,
    "denoised": true,
    "direct_light_sampling": "importance",
    "clamp_direct": 64.0,
    "clamp_indirect": 16.0
  },
  "timings_ms": {
    "bvh_build": 110.5024642944336,
    "render": 5419768.5,
    "denoise": 20.261856079101562,
    "avif_encode": 2361.935987,
    "total": 5423704.55362
  },
  "hdr_avif": {
    "bit_depth": 10,
    "yuv_format": "4:4:4",
    "full_range": true,
    "cicp": [
      9,
      16,
      9
    ],
    "diffuse_white_nits": 203,
    "peak_nits": 1000,
    "lossless": true,
    "max_cll": 1000,
    "max_pall": 10
  },
  "memory": {
    "peak_device_bytes": 4636803072,
    "peak_tracked_device_bytes": 2855035236
  },
  "geometry": {
    "objects": 450,
    "instances": 450,
    "unique_meshes": 0,
    "mesh_triangles": 0,
    "gas_count": 450
  },
  "performance": {
    "traced_rays": 292746357219,
    "rays_per_second": 54014550.108367175
  },
  "firefly": {
    "direct_clamped_contributions": 31020542,
    "indirect_clamped_contributions": 2731629
  },
  "volume": {
    "volume_density_evaluations": 311879096557,
    "volume_real_collisions": 5956444081,
    "volume_light_samples": 57365681930,
    "volume_majorant_violations": 0,
    "volume_tracking_overflows": 0
  },
  "water": {
    "water_height_evaluations": 259930913055,
    "water_tile_tests": 25693296556,
    "water_roots_reported": 6822905424,
    "water_medium_segments": 2437485270,
    "water_solver_overflows": 0,
    "water_medium_errors": 0,
    "water_rough_nee_attempts": 16601428480,
    "water_rough_nee_contributions": 4778787039,
    "water_delta_splits": 0
  }
}
